gitflow_analytics/__init__.py
gitflow_analytics/_version.py
gitflow_analytics/cli.py
gitflow_analytics/config.py
gitflow_analytics/constants.py
gitflow_analytics/verify_activity.py
gitflow_analytics/classification/__init__.py
gitflow_analytics/classification/batch_classifier.py
gitflow_analytics/classification/classifier.py
gitflow_analytics/classification/feature_extractor.py
gitflow_analytics/classification/linguist_analyzer.py
gitflow_analytics/classification/model.py
gitflow_analytics/cli_wizards/__init__.py
gitflow_analytics/cli_wizards/install_wizard.py
gitflow_analytics/cli_wizards/menu.py
gitflow_analytics/cli_wizards/run_launcher.py
gitflow_analytics/config/__init__.py
gitflow_analytics/config/aliases.py
gitflow_analytics/config/errors.py
gitflow_analytics/config/loader.py
gitflow_analytics/config/profiles.py
gitflow_analytics/config/repository.py
gitflow_analytics/config/schema.py
gitflow_analytics/config/validator.py
gitflow_analytics/core/__init__.py
gitflow_analytics/core/analyzer.py
gitflow_analytics/core/branch_mapper.py
gitflow_analytics/core/cache.py
gitflow_analytics/core/data_fetcher.py
gitflow_analytics/core/git_auth.py
gitflow_analytics/core/git_timeout_wrapper.py
gitflow_analytics/core/identity.py
gitflow_analytics/core/metrics_storage.py
gitflow_analytics/core/progress.py
gitflow_analytics/core/schema_version.py
gitflow_analytics/core/subprocess_git.py
gitflow_analytics/extractors/__init__.py
gitflow_analytics/extractors/base.py
gitflow_analytics/extractors/ml_tickets.py
gitflow_analytics/extractors/story_points.py
gitflow_analytics/extractors/tickets.py
gitflow_analytics/identity_llm/__init__.py
gitflow_analytics/identity_llm/analysis_pass.py
gitflow_analytics/identity_llm/analyzer.py
gitflow_analytics/identity_llm/models.py
gitflow_analytics/integrations/__init__.py
gitflow_analytics/integrations/github_integration.py
gitflow_analytics/integrations/jira_integration.py
gitflow_analytics/integrations/orchestrator.py
gitflow_analytics-3.13.9.dist-info/licenses/LICENSE
gitflow_analytics-3.13.9.dist-info/METADATA
gitflow_analytics-3.13.9.dist-info/WHEEL
gitflow_analytics-3.13.9.dist-info/entry_points.txt
gitflow_analytics-3.13.9.dist-info/top_level.txt
gitflow_analytics-3.13.9.dist-info/RECORD
