Metadata-Version: 2.4
Name: gitflow-analytics
Version: 3.13.9
Summary: Analyze Git repositories for developer productivity insights
Author-email: Bob Matyas <bobmatnyc@gmail.com>
License: MIT
Project-URL: Homepage, https://github.com/bobmatnyc/gitflow-analytics
Project-URL: Documentation, https://github.com/bobmatnyc/gitflow-analytics/blob/main/README.md
Project-URL: Repository, https://github.com/bobmatnyc/gitflow-analytics
Project-URL: Issues, https://github.com/bobmatnyc/gitflow-analytics/issues
Keywords: git,analytics,productivity,metrics,development
Classifier: Development Status :: 5 - Production/Stable
Classifier: Intended Audience :: Developers
Classifier: Programming Language :: Python :: 3
Classifier: Programming Language :: Python :: 3.9
Classifier: Programming Language :: Python :: 3.10
Classifier: Programming Language :: Python :: 3.11
Classifier: Programming Language :: Python :: 3.12
Classifier: Topic :: Software Development :: Version Control :: Git
Classifier: Topic :: Software Development :: Quality Assurance
Requires-Python: >=3.9
License-File: LICENSE
Requires-Dist: click>=8.1
Requires-Dist: gitpython>=3.1
Requires-Dist: pygithub>=2.0
Requires-Dist: tqdm>=4.65
Requires-Dist: sqlalchemy>=2.0
Requires-Dist: pandas>=2.0
Requires-Dist: pyyaml>=6.0
Requires-Dist: python-dateutil>=2.8
Requires-Dist: python-dotenv>=1.0
Requires-Dist: rich>=13.0.0
Requires-Dist: tabulate>=0.9.0
Requires-Dist: spacy>=3.7.0
Requires-Dist: scikit-learn>=1.3.0
Requires-Dist: openai>=1.30.0
Requires-Dist: tiktoken>=0.7.0
Requires-Dist: numpy>=1.24.0
Provides-Extra: dev
Requires-Dist: pytest>=7.0; extra == "dev"
Requires-Dist: pytest-cov>=4.0; extra == "dev"
Requires-Dist: pytest-mock>=3.0; extra == "dev"
Requires-Dist: ruff>=0.1.0; extra == "dev"
Requires-Dist: mypy>=1.0; extra == "dev"
Requires-Dist: black>=23.0; extra == "dev"
Requires-Dist: isort>=5.0; extra == "dev"
Requires-Dist: bandit[toml]>=1.7; extra == "dev"
Requires-Dist: safety>=2.0; extra == "dev"
Requires-Dist: python-semantic-release>=8.0.0; extra == "dev"
Requires-Dist: types-PyYAML>=6.0; extra == "dev"
Requires-Dist: types-requests>=2.28; extra == "dev"
Provides-Extra: github
Requires-Dist: pygithub>=1.58; extra == "github"
Provides-Extra: all
Requires-Dist: gitflow-analytics[github]; extra == "all"
Dynamic: license-file
